hm_pyhelper/__init__.py
hm_pyhelper/exceptions.py
hm_pyhelper/gateway_mfr
hm_pyhelper/hardware_definitions.py
hm_pyhelper/lock_singleton.py
hm_pyhelper/logger.py
hm_pyhelper/main.py
hm_pyhelper/miner_param.py
hm_pyhelper/diagnostics/__init__.py
hm_pyhelper/diagnostics/diagnostic.py
hm_pyhelper/diagnostics/diagnostics_report.py
hm_pyhelper/miner_json_rpc/__init__.py
hm_pyhelper/miner_json_rpc/client.py
hm_pyhelper/miner_json_rpc/exceptions.py
hm_pyhelper/tests/__init__.py
hm_pyhelper/tests/test_diagnostic_report.py
hm_pyhelper/tests/test_get_mac_address.py
hm_pyhelper/tests/test_hardware_definitions.py
hm_pyhelper/tests/test_lock_singleton.py
hm_pyhelper/tests/test_logger.py
hm_pyhelper/tests/test_miner_json_rpc.py
hm_pyhelper/tests/test_miner_param.py
forked_hm_diag-0.13.0.dist-info/LICENSE
forked_hm_diag-0.13.0.dist-info/METADATA
forked_hm_diag-0.13.0.dist-info/WHEEL
forked_hm_diag-0.13.0.dist-info/top_level.txt
forked_hm_diag-0.13.0.dist-info/RECORD
