Metadata-Version: 2.1
Name: forked-hm-diag
Version: 0.13.0
Summary: Helium Python Helper
Home-page: https://github.com/jonzky/hm-pyhelper
Author: Jon
Author-email: JonZakay@aol.com
License: UNKNOWN
Project-URL: Bug Tracker, https://github.com/jonzky/hm-pyhelper/issues
Platform: UNKNOWN
License-File: LICENSE
Requires-Dist: requests (>=2.26.0)
Requires-Dist: jsonrpcclient (==3.3.6)
Requires-Dist: retry (==0.9.2)
